[
  {
    "rating": "2",
    "message": "r3r2r2",
    "domain": "jysk.dk",
    "email": "test@test.dk",
    "name": "",
    "orderId": "",
    "createdAt": "2026-04-14T15:19:15.319Z"
  },
  {
    "rating": "2",
    "message": "ygui",
    "domain": "jysk.dk",
    "email": "test@test.dk",
    "name": "",
    "orderId": "",
    "createdAt": "2026-04-15T05:07:39.324Z"
  },
  {
    "rating": "2",
    "message": "egwgeq",
    "domain": "jysk.dk",
    "email": "test@test.dk",
    "name": "",
    "orderId": "",
    "createdAt": "2026-04-15T05:19:10.328Z"
  },
  {
    "rating": "2",
    "message": "rgg4e",
    "domain": "jysk.dk",
    "email": "test@test.dk",
    "name": "Niels",
    "orderId": "1234",
    "createdAt": "2026-04-15T05:21:07.946Z"
  },
  {
    "rating": "2",
    "message": "hth435",
    "domain": "jysk.dk",
    "email": "test@test.dk",
    "name": "",
    "orderId": "",
    "createdAt": "2026-04-15T05:31:11.016Z"
  },
  {
    "rating": "2",
    "message": "g4f3f",
    "domain": "jysk.dk",
    "email": "test@test.dk",
    "name": "Niels dillerfdaller",
    "orderId": "4g43g3",
    "createdAt": "2026-04-15T05:34:25.481Z"
  }
]